README.md
setup.cfg
setup.py
bbx_ninja/__init__.py
bbx_ninja.egg-info/PKG-INFO
bbx_ninja.egg-info/SOURCES.txt
bbx_ninja.egg-info/dependency_links.txt
bbx_ninja.egg-info/requires.txt
bbx_ninja.egg-info/top_level.txt
bbx_ninja/dataset_related/__init__.py
bbx_ninja/dataset_related/check_squad_integrity.py
bbx_ninja/dataset_related/sample_large_ds.py
bbx_ninja/knowledge_graph/__init__.py
bbx_ninja/knowledge_graph/generate_qa_from_wikidata.py
bbx_ninja/knowledge_graph/sparql_queries.py
bbx_ninja/knowledge_graph/util.py
bbx_ninja/web_crawler/__init__.py
bbx_ninja/web_crawler/cooler.py