Metadata-Version: 1.2
Name: bbx-ninja
Version: 0.0.7
Summary: bbx repo to make my life easier.
Home-page: https://github.com/gabinguo/
Author: Kunpeng GUO
Author-email: kunpeng.guo@univ-st-etienne.fr
License: MIT
Download-URL: https://github.com/gabinguo/bbx/releases/download/v0.0.7/bbx_ninja_v0.0.7.tar.gz
Keywords: scripts,anything,python
Platform: UNKNOWN
Classifier: Development Status :: 3 - Alpha
Classifier: Intended Audience :: Developers
Classifier: Topic :: Scientific/Engineering :: Artificial Intelligence
Classifier: License :: OSI Approved :: MIT License
Classifier: Programming Language :: Python :: 3
Requires-Python: >=3.6.0
